evolutionary_search/__init__.py
evolutionary_search/cv.py
evolutionary_search/optimize.py
sklearn_deap-0.3.0.dist-info/LICENSE.txt
sklearn_deap-0.3.0.dist-info/METADATA
sklearn_deap-0.3.0.dist-info/WHEEL
sklearn_deap-0.3.0.dist-info/top_level.txt
sklearn_deap-0.3.0.dist-info/RECORD
