Metadata-Version: 2.1
Name: sklearn-deap
Version: 0.3.0
Summary: Use evolutionary algorithms instead of gridsearch in scikit-learn.
Home-page: https://github.com/rsteca/sklearn-deap
Author: Rodrigo
Author-email: UNKNOWN
License: UNKNOWN
Download-URL: https://github.com/rsteca/sklearn-deap/tarball/0.3.0
Platform: UNKNOWN
Classifier: Development Status :: 4 - Beta
Classifier: Programming Language :: Python :: 2
Classifier: Programming Language :: Python :: 2.6
Classifier: Programming Language :: Python :: 2.7
Classifier: Programming Language :: Python :: 3
Classifier: Programming Language :: Python :: 3.3
Classifier: Programming Language :: Python :: 3.4
Classifier: Programming Language :: Python
Classifier: Intended Audience :: Science/Research
Classifier: Intended Audience :: Developers
Requires-Dist: numpy (>=1.9.3)
Requires-Dist: scipy (>=0.16.0)
Requires-Dist: deap (>=1.0.2)
Requires-Dist: scikit-learn (>=0.24.0)
